{
  "source": "idokep.hu",
  "location": "Nyiracsad",
  "fronthatas": "Nem lesz front felettünk",
  "focim": "Szeles idő sok napsütéssel",
  "updated": "2026.04.03. 02:03",
  "flow_last_run": "2026.04.03. 02:03",
  "current": {
    "temperature": 10,
    "condition": "Gyengén felhős",
    "icon": "☁️"
  },
  "forecast_7d": [
    {
      "day": "Péntek",
      "max": 18,
      "min": 7,
      "condition": "közepesen felhős",
      "icon": "☁️",
      "alert": null
    },
    {
      "day": "Szombat",
      "max": 17,
      "min": 3,
      "condition": "gyengén felhős",
      "icon": "☁️",
      "alert": null
    },
    {
      "day": "Vasárnap",
      "max": 20,
      "min": 4,
      "condition": "gyengén felhős",
      "icon": "☁️",
      "alert": null
    },
    {
      "day": "Hétfő",
      "max": 21,
      "min": 8,
      "condition": "közepesen felhős",
      "icon": "☁️",
      "alert": null
    },
    {
      "day": "Kedd",
      "max": 20,
      "min": 5,
      "condition": "gyengén felhős",
      "icon": "☁️",
      "alert": null
    },
    {
      "day": "Szerda",
      "max": 19,
      "min": 4,
      "condition": "gyengén felhős",
      "icon": "☁️",
      "alert": null
    },
    {
      "day": "Csütörtök",
      "max": 18,
      "min": 4,
      "condition": "közepesen felhős",
      "icon": "☁️",
      "alert": null
    }
  ],
  "sun": {
    "sunrise": "6:06",
    "sunset": "19:04",
    "is_night": true
  }
}