{
  "source": "idokep.hu",
  "location": "Hajduhadhaz",
  "fronthatas": "Hidegfronti jellegű tünetek jelentkezhetnek",
  "focim": "Kissé szeles, kellemesen meleg idő",
  "updated": "2026.07.20. 23:21",
  "flow_last_run": "2026.07.20. 23:21",
  "current": {
    "temperature": 17,
    "condition": "Gyengén felhős",
    "icon": "☁️"
  },
  "forecast_7d": [
    {
      "day": "Kedd",
      "max": 28,
      "min": 16,
      "condition": "gyengén felhős",
      "icon": "☁️",
      "alert": null
    },
    {
      "day": "Szerda",
      "max": 26,
      "min": 16,
      "condition": "gyengén felhős",
      "icon": "☁️",
      "alert": null
    },
    {
      "day": "Csütörtök",
      "max": 28,
      "min": 12,
      "condition": "zápor",
      "icon": "🌧️",
      "alert": null
    },
    {
      "day": "Péntek",
      "max": 25,
      "min": 11,
      "condition": "közepesen felhős",
      "icon": "☁️",
      "alert": null
    },
    {
      "day": "Szombat",
      "max": 28,
      "min": 12,
      "condition": "gyengén felhős",
      "icon": "☁️",
      "alert": null
    },
    {
      "day": "Vasárnap",
      "max": 31,
      "min": 14,
      "condition": "zápor",
      "icon": "🌧️",
      "alert": null
    },
    {
      "day": "Hétfő",
      "max": 31,
      "min": 16,
      "condition": "közepesen felhős",
      "icon": "☁️",
      "alert": null
    }
  ],
  "sun": {
    "sunrise": "4:57",
    "sunset": "20:23",
    "is_night": true
  }
}