{
  "source": "idokep.hu",
  "location": "Hajduhadhaz",
  "fronthatas": "Hidegfronti hatás érvényesül",
  "focim": "Záporokkal, zivatarokkal indul a hét",
  "updated": "2026.05.31. 20:01",
  "flow_last_run": "2026.05.31. 20:01",
  "current": {
    "temperature": 22,
    "condition": "Erősen felhős",
    "icon": "☁️"
  },
  "forecast_7d": [
    {
      "day": "Hétfő",
      "max": 25,
      "min": 12,
      "condition": "zivatar",
      "icon": "⛈️",
      "alert": null
    },
    {
      "day": "Kedd",
      "max": 27,
      "min": 12,
      "condition": "zápor",
      "icon": "🌧️",
      "alert": null
    },
    {
      "day": "Szerda",
      "max": 27,
      "min": 13,
      "condition": "közepesen felhős",
      "icon": "☁️",
      "alert": null
    },
    {
      "day": "Csütörtök",
      "max": 25,
      "min": 15,
      "condition": "zápor",
      "icon": "🌧️",
      "alert": null
    },
    {
      "day": "Péntek",
      "max": 26,
      "min": 13,
      "condition": "erősen felhős",
      "icon": "☁️",
      "alert": null
    },
    {
      "day": "Szombat",
      "max": 27,
      "min": 14,
      "condition": "zápor",
      "icon": "🌧️",
      "alert": null
    },
    {
      "day": "Vasárnap",
      "max": 27,
      "min": 14,
      "condition": "zivatar",
      "icon": "⛈️",
      "alert": null
    }
  ],
  "sun": {
    "sunrise": "4:39",
    "sunset": "20:22",
    "is_night": false
  }
}