{
  "source": "idokep.hu",
  "location": "Hajduhadhaz",
  "fronthatas": "Gyenge hidegfronti hatás",
  "focim": "Hőségmentes csütörtök",
  "updated": "2026.05.28. 11:03",
  "flow_last_run": "2026.05.28. 11:03",
  "current": {
    "temperature": 23,
    "condition": "Derült",
    "icon": "🌙"
  },
  "forecast_7d": [
    {
      "day": "Csütörtök",
      "max": 24,
      "min": 12,
      "condition": "közepesen felhős",
      "icon": "☁️",
      "alert": null
    },
    {
      "day": "Péntek",
      "max": 23,
      "min": 8,
      "condition": "közepesen felhős",
      "icon": "☁️",
      "alert": null
    },
    {
      "day": "Szombat",
      "max": 26,
      "min": 9,
      "condition": "zápor",
      "icon": "🌧️",
      "alert": null
    },
    {
      "day": "Vasárnap",
      "max": 27,
      "min": 12,
      "condition": "közepesen felhős",
      "icon": "☁️",
      "alert": null
    },
    {
      "day": "Hétfő",
      "max": 26,
      "min": 15,
      "condition": "zápor",
      "icon": "🌧️",
      "alert": null
    },
    {
      "day": "Kedd",
      "max": 28,
      "min": 14,
      "condition": "közepesen felhős",
      "icon": "☁️",
      "alert": null
    },
    {
      "day": "Szerda",
      "max": 27,
      "min": 15,
      "condition": "zivatar",
      "icon": "⛈️",
      "alert": null
    }
  ],
  "sun": {
    "sunrise": "4:42",
    "sunset": "20:19",
    "is_night": false
  }
}