{
  "source": "idokep.hu",
  "location": "Nyiracsad",
  "fronthatas": "Nem várható fronthatás",
  "focim": "Kissé szeles nyári idővel indul a hét",
  "updated": "2026.07.13. 13:30",
  "flow_last_run": "2026.07.13. 13:30",
  "current": {
    "temperature": 27,
    "condition": "Közepesen felhős",
    "icon": "☁️"
  },
  "forecast_7d": [
    {
      "day": "Hétfő",
      "max": 26,
      "min": 15,
      "condition": "közepesen felhős",
      "icon": "☁️",
      "alert": null
    },
    {
      "day": "Kedd",
      "max": 30,
      "min": 17,
      "condition": "zápor",
      "icon": "🌧️",
      "alert": null
    },
    {
      "day": "Szerda",
      "max": 30,
      "min": 19,
      "condition": "zivatar",
      "icon": "⛈️",
      "alert": null
    },
    {
      "day": "Csütörtök",
      "max": 32,
      "min": 17,
      "condition": "zápor",
      "icon": "🌧️",
      "alert": null
    },
    {
      "day": "Péntek",
      "max": 33,
      "min": 17,
      "condition": "gyengén felhős",
      "icon": "☁️",
      "alert": null
    },
    {
      "day": "Szombat",
      "max": 31,
      "min": 17,
      "condition": "zápor",
      "icon": "🌧️",
      "alert": null
    },
    {
      "day": "Vasárnap",
      "max": 29,
      "min": 16,
      "condition": "zápor",
      "icon": "🌧️",
      "alert": null
    }
  ],
  "sun": {
    "sunrise": "4:48",
    "sunset": "20:27",
    "is_night": false
  }
}