{
  "source": "idokep.hu",
  "location": "Hajduhadhaz",
  "fronthatas": "Nem lesz front felettünk",
  "updated": "2026.03.14. 17:54",
  "flow_last_run": "2026.03.14. 17:54",
  "current": {
    "temperature": 13,
    "condition": "Gyengén felhős",
    "icon": "☁️"
  },
  "forecast_7d": [
    {
      "day": "Szombat",
      "max": 18,
      "min": 2,
      "condition": "gyengén felhős",
      "icon": "☁️",
      "alert": null
    },
    {
      "day": "Vasárnap",
      "max": 17,
      "min": -1,
      "condition": "derült",
      "icon": "🌙",
      "alert": null
    },
    {
      "day": "Hétfő",
      "max": 16,
      "min": -2,
      "condition": "közepesen felhős",
      "icon": "☁️",
      "alert": null
    },
    {
      "day": "Kedd",
      "max": 15,
      "min": 1,
      "condition": "erősen felhős",
      "icon": "☁️",
      "alert": null
    },
    {
      "day": "Szerda",
      "max": 13,
      "min": 3,
      "condition": "zápor",
      "icon": "🌧️",
      "alert": null
    },
    {
      "day": "Csütörtök",
      "max": 14,
      "min": 2,
      "condition": "közepesen felhős",
      "icon": "☁️",
      "alert": null
    },
    {
      "day": "Péntek",
      "max": 13,
      "min": 1,
      "condition": "erősen felhős",
      "icon": "☁️",
      "alert": null
    }
  ],
  "sun": {
    "sunrise": "5:46",
    "sunset": "17:36",
    "is_night": true
  }
}