[
  {
    "csatorna": "AMC",
    "kezdes": "20260405134500 +0000",
    "vege": "20260405155500 +0000",
    "cim": "Piedone, a zsaru"
  },
  {
    "csatorna": "AMC",
    "kezdes": "20260405155500 +0000",
    "vege": "20260405180000 +0000",
    "cim": "Dutyi dili"
  },
  {
    "csatorna": "AMC",
    "kezdes": "20260405180000 +0000",
    "vege": "20260405201000 +0000",
    "cim": "Pancser police"
  },
  {
    "csatorna": "AMC",
    "kezdes": "20260405201000 +0000",
    "vege": "20260405221500 +0000",
    "cim": "Kígyók a fedélzeten"
  },
  {
    "csatorna": "AMC",
    "kezdes": "20260405221500 +0000",
    "vege": "20260406001000 +0000",
    "cim": "Torrente 4"
  },
  {
    "csatorna": "AXN",
    "kezdes": "20260405124500 +0000",
    "vege": "20260405134500 +0000",
    "cim": "FBI - New York különleges ügynökei"
  },
  {
    "csatorna": "AXN",
    "kezdes": "20260405134500 +0000",
    "vege": "20260405144500 +0000",
    "cim": "FBI - New York különleges ügynökei"
  },
  {
    "csatorna": "AXN",
    "kezdes": "20260405144500 +0000",
    "vege": "20260405165500 +0000",
    "cim": "Szellemirtók"
  },
  {
    "csatorna": "AXN",
    "kezdes": "20260405165500 +0000",
    "vege": "20260405190000 +0000",
    "cim": "A cipőbűvölő"
  },
  {
    "csatorna": "AXN",
    "kezdes": "20260405190000 +0000",
    "vege": "20260405211000 +0000",
    "cim": "WAR"
  },
  {
    "csatorna": "AXN",
    "kezdes": "20260405211000 +0000",
    "vege": "20260405231000 +0000",
    "cim": "Street Fighter - Harc a végsőkig"
  },
  {
    "csatorna": "AXN",
    "kezdes": "20260405231000 +0000",
    "vege": "20260405235500 +0000",
    "cim": "FBI - New York különleges ügynökei"
  },
  {
    "csatorna": "AXN",
    "kezdes": "20260405235500 +0000",
    "vege": "20260406004000 +0000",
    "cim": "FBI - New York különleges ügynökei"
  },
  {
    "csatorna": "FILM4",
    "kezdes": "20260405124500 +0000",
    "vege": "20260405143500 +0000",
    "cim": "Mentsük meg Flórát!"
  },
  {
    "csatorna": "FILM4",
    "kezdes": "20260405143500 +0000",
    "vege": "20260405161500 +0000",
    "cim": "Reggeli show: Gyilkosság az étlapon"
  },
  {
    "csatorna": "FILM4",
    "kezdes": "20260405161500 +0000",
    "vege": "20260405180000 +0000",
    "cim": "Családos őrület"
  },
  {
    "csatorna": "FILM4",
    "kezdes": "20260405180000 +0000",
    "vege": "20260405200000 +0000",
    "cim": "Hudson Hawk - Egy mestertolvaj aranyat ér"
  },
  {
    "csatorna": "FILM4",
    "kezdes": "20260405200000 +0000",
    "vege": "20260405221000 +0000",
    "cim": "Marston professzor és a két Wonder Woman"
  },
  {
    "csatorna": "FILM4",
    "kezdes": "20260405221000 +0000",
    "vege": "20260406004000 +0000",
    "cim": "Egy becsületbeli ügy"
  },
  {
    "csatorna": "FILMCAFE",
    "kezdes": "20260405140500 +0000",
    "vege": "20260405160500 +0000",
    "cim": "Dirty Dancing - Piszkos tánc"
  },
  {
    "csatorna": "FILMCAFE",
    "kezdes": "20260405160500 +0000",
    "vege": "20260405180000 +0000",
    "cim": "Az utazó"
  },
  {
    "csatorna": "FILMCAFE",
    "kezdes": "20260405180000 +0000",
    "vege": "20260405200000 +0000",
    "cim": "A vágyak szigete"
  },
  {
    "csatorna": "FILMCAFE",
    "kezdes": "20260405200000 +0000",
    "vege": "20260405223500 +0000",
    "cim": "Elemi ösztön"
  },
  {
    "csatorna": "FILMCAFE",
    "kezdes": "20260405223500 +0000",
    "vege": "20260406003000 +0000",
    "cim": "Szüzet szüntess"
  },
  {
    "csatorna": "FILMMANIA",
    "kezdes": "20260405135500 +0000",
    "vege": "20260405162000 +0000",
    "cim": "Fekete tulipán"
  },
  {
    "csatorna": "FILMMANIA",
    "kezdes": "20260405162000 +0000",
    "vege": "20260405180000 +0000",
    "cim": "Az emlékek őre"
  },
  {
    "csatorna": "FILMMANIA",
    "kezdes": "20260405180000 +0000",
    "vege": "20260405202000 +0000",
    "cim": "Pókember"
  },
  {
    "csatorna": "FILMMANIA",
    "kezdes": "20260405202000 +0000",
    "vege": "20260405221500 +0000",
    "cim": "A barlang mélyén"
  },
  {
    "csatorna": "FILMMANIA",
    "kezdes": "20260405221500 +0000",
    "vege": "20260406000500 +0000",
    "cim": "Fekete sas"
  },
  {
    "csatorna": "FILMPLUSSZ",
    "kezdes": "20260405124500 +0000",
    "vege": "20260405153000 +0000",
    "cim": "Halálos iramban 8."
  },
  {
    "csatorna": "FILMPLUSSZ",
    "kezdes": "20260405153000 +0000",
    "vege": "20260405181500 +0000",
    "cim": "Halálos iramban 9."
  },
  {
    "csatorna": "FILMPLUSSZ",
    "kezdes": "20260405181500 +0000",
    "vege": "20260405210000 +0000",
    "cim": "Halálos iramban: Hobbs & Shaw"
  },
  {
    "csatorna": "FILMPLUSSZ",
    "kezdes": "20260405210000 +0000",
    "vege": "20260405232000 +0000",
    "cim": "Halálos fegyver"
  },
  {
    "csatorna": "FILMPLUSSZ",
    "kezdes": "20260405232000 +0000",
    "vege": "20260406030000 +0000",
    "cim": "Vonalban vagy"
  },
  {
    "csatorna": "MOZIPLUSZ",
    "kezdes": "20260405122000 +0000",
    "vege": "20260405144000 +0000",
    "cim": "A múmia visszatér"
  },
  {
    "csatorna": "MOZIPLUSZ",
    "kezdes": "20260405144000 +0000",
    "vege": "20260405164500 +0000",
    "cim": "Amerikába jöttem"
  },
  {
    "csatorna": "MOZIPLUSZ",
    "kezdes": "20260405164500 +0000",
    "vege": "20260405190000 +0000",
    "cim": "Die Hard 3: Az élet mindig drága"
  },
  {
    "csatorna": "MOZIPLUSZ",
    "kezdes": "20260405190000 +0000",
    "vege": "20260405220000 +0000",
    "cim": "Mission: Impossible - Leszámolás - Első Rész"
  },
  {
    "csatorna": "MOZIPLUSZ",
    "kezdes": "20260405220000 +0000",
    "vege": "20260406000000 +0000",
    "cim": "A Múmia - A Sárkánycsászár sírja"
  },
  {
    "csatorna": "MOZIVERZUM",
    "kezdes": "20260405140000 +0000",
    "vege": "20260405152500 +0000",
    "cim": "Maci Laci"
  },
  {
    "csatorna": "MOZIVERZUM",
    "kezdes": "20260405152500 +0000",
    "vege": "20260405172500 +0000",
    "cim": "Egy kutya négy útja"
  },
  {
    "csatorna": "MOZIVERZUM",
    "kezdes": "20260405172500 +0000",
    "vege": "20260405190000 +0000",
    "cim": "Shrek"
  },
  {
    "csatorna": "MOZIVERZUM",
    "kezdes": "20260405190000 +0000",
    "vege": "20260405214000 +0000",
    "cim": "Pókember: A pókverzumon át"
  },
  {
    "csatorna": "MOZIVERZUM",
    "kezdes": "20260405214000 +0000",
    "vege": "20260405232500 +0000",
    "cim": "Vakáció"
  },
  {
    "csatorna": "MOZIVERZUM",
    "kezdes": "20260405232500 +0000",
    "vege": "20260406005500 +0000",
    "cim": "Fedőneve: Banshee"
  },
  {
    "csatorna": "NICKELODEON",
    "kezdes": "20260405120500 +0000",
    "vege": "20260405122000 +0000",
    "cim": "A Lármás család"
  },
  {
    "csatorna": "NICKELODEON",
    "kezdes": "20260405122000 +0000",
    "vege": "20260405124000 +0000",
    "cim": "A Wylde-Pak bagázs"
  },
  {
    "csatorna": "NICKELODEON",
    "kezdes": "20260405124000 +0000",
    "vege": "20260405130500 +0000",
    "cim": "A Wylde-Pak bagázs"
  },
  {
    "csatorna": "NICKELODEON",
    "kezdes": "20260405130500 +0000",
    "vege": "20260405133000 +0000",
    "cim": "SpongyaBob KockaNadrág"
  },
  {
    "csatorna": "NICKELODEON",
    "kezdes": "20260405133000 +0000",
    "vege": "20260405135000 +0000",
    "cim": "A Marsupilamik"
  },
  {
    "csatorna": "NICKELODEON",
    "kezdes": "20260405135000 +0000",
    "vege": "20260405141500 +0000",
    "cim": "SpongyaBob KockaNadrág"
  },
  {
    "csatorna": "NICKELODEON",
    "kezdes": "20260405141500 +0000",
    "vege": "20260405144000 +0000",
    "cim": "SpongyaBob KockaNadrág"
  },
  {
    "csatorna": "NICKELODEON",
    "kezdes": "20260405144000 +0000",
    "vege": "20260405150500 +0000",
    "cim": "SpongyaBob KockaNadrág"
  },
  {
    "csatorna": "NICKELODEON",
    "kezdes": "20260405150500 +0000",
    "vege": "20260405152500 +0000",
    "cim": "That Girl Lay Lay"
  },
  {
    "csatorna": "NICKELODEON",
    "kezdes": "20260405152500 +0000",
    "vege": "20260405155000 +0000",
    "cim": "That Girl Lay Lay"
  },
  {
    "csatorna": "NICKELODEON",
    "kezdes": "20260405155000 +0000",
    "vege": "20260405161500 +0000",
    "cim": "Veszélyes Henry"
  },
  {
    "csatorna": "NICKELODEON",
    "kezdes": "20260405161500 +0000",
    "vege": "20260405163500 +0000",
    "cim": "Veszélyes Henry"
  },
  {
    "csatorna": "NICKELODEON",
    "kezdes": "20260405163500 +0000",
    "vege": "20260405170000 +0000",
    "cim": "Veszélyes Osztag"
  },
  {
    "csatorna": "NICKELODEON",
    "kezdes": "20260405170000 +0000",
    "vege": "20260405172500 +0000",
    "cim": "iCarly"
  },
  {
    "csatorna": "NICKELODEON",
    "kezdes": "20260405172500 +0000",
    "vege": "20260405175000 +0000",
    "cim": "iCarly"
  },
  {
    "csatorna": "NICKELODEON",
    "kezdes": "20260405175000 +0000",
    "vege": "20260405181500 +0000",
    "cim": "V, mint Viktória"
  },
  {
    "csatorna": "NICKELODEON",
    "kezdes": "20260405181500 +0000",
    "vege": "20260405184000 +0000",
    "cim": "Sam és Cat"
  },
  {
    "csatorna": "NICKELODEON",
    "kezdes": "20260405184000 +0000",
    "vege": "20260405190000 +0000",
    "cim": "Mesék a Tini Nindzsa Teknőcökről"
  },
  {
    "csatorna": "NICKELODEON",
    "kezdes": "20260405190000 +0000",
    "vege": "20260405192500 +0000",
    "cim": "Mesék a Tini Nindzsa Teknőcökről"
  },
  {
    "csatorna": "NICKELODEON",
    "kezdes": "20260405192500 +0000",
    "vege": "20260405195000 +0000",
    "cim": "SpongyaBob KockaNadrág"
  },
  {
    "csatorna": "NICKELODEON",
    "kezdes": "20260405195000 +0000",
    "vege": "20260405201500 +0000",
    "cim": "SpongyaBob KockaNadrág"
  },
  {
    "csatorna": "NICKELODEON",
    "kezdes": "20260405201500 +0000",
    "vege": "20260405203500 +0000",
    "cim": "A Marsupilamik"
  },
  {
    "csatorna": "NICKELODEON",
    "kezdes": "20260405203500 +0000",
    "vege": "20260405210000 +0000",
    "cim": "Szipi & Szuper"
  },
  {
    "csatorna": "NICKELODEON",
    "kezdes": "20260405210000 +0000",
    "vege": "20260405212000 +0000",
    "cim": "Szipi & Szuper"
  },
  {
    "csatorna": "NICKELODEON",
    "kezdes": "20260405212000 +0000",
    "vege": "20260405214500 +0000",
    "cim": "Csillag Patrik műsora"
  },
  {
    "csatorna": "NICKELODEON",
    "kezdes": "20260405214500 +0000",
    "vege": "20260405221000 +0000",
    "cim": "Csillag Patrik műsora"
  },
  {
    "csatorna": "NICKELODEON",
    "kezdes": "20260405221000 +0000",
    "vege": "20260405223000 +0000",
    "cim": "SpongyaBob KockaNadrág"
  },
  {
    "csatorna": "NICKELODEON",
    "kezdes": "20260405223000 +0000",
    "vege": "20260405224500 +0000",
    "cim": "SpongyaBob KockaNadrág"
  },
  {
    "csatorna": "NICKELODEON",
    "kezdes": "20260405224500 +0000",
    "vege": "20260405231000 +0000",
    "cim": "A Thunderman-család: Beépített küldetés"
  },
  {
    "csatorna": "NICKELODEON",
    "kezdes": "20260405231000 +0000",
    "vege": "20260405233500 +0000",
    "cim": "Veszélyes Osztag"
  },
  {
    "csatorna": "NICKELODEON",
    "kezdes": "20260405233500 +0000",
    "vege": "20260405235500 +0000",
    "cim": "Veszélyes Henry"
  },
  {
    "csatorna": "NICKELODEON",
    "kezdes": "20260405235500 +0000",
    "vege": "20260406002000 +0000",
    "cim": "A Lármás család"
  },
  {
    "csatorna": "OZONETV",
    "kezdes": "20260405120000 +0000",
    "vege": "20260405123000 +0000",
    "cim": "Garázs"
  },
  {
    "csatorna": "OZONETV",
    "kezdes": "20260405123000 +0000",
    "vege": "20260405130000 +0000",
    "cim": "Garázs"
  },
  {
    "csatorna": "OZONETV",
    "kezdes": "20260405130000 +0000",
    "vege": "20260405140000 +0000",
    "cim": "Ozone utazás"
  },
  {
    "csatorna": "OZONETV",
    "kezdes": "20260405140000 +0000",
    "vege": "20260405143000 +0000",
    "cim": "Hogyan készül? Megmutatjuk!"
  },
  {
    "csatorna": "OZONETV",
    "kezdes": "20260405143000 +0000",
    "vege": "20260405150000 +0000",
    "cim": "Hogyan készül? Megmutatjuk!"
  },
  {
    "csatorna": "OZONETV",
    "kezdes": "20260405150000 +0000",
    "vege": "20260405153000 +0000",
    "cim": "Raktárvadászok"
  },
  {
    "csatorna": "OZONETV",
    "kezdes": "20260405153000 +0000",
    "vege": "20260405160000 +0000",
    "cim": "Raktárvadászok"
  },
  {
    "csatorna": "OZONETV",
    "kezdes": "20260405160000 +0000",
    "vege": "20260405163000 +0000",
    "cim": "Raktárvadászok"
  },
  {
    "csatorna": "OZONETV",
    "kezdes": "20260405163000 +0000",
    "vege": "20260405170000 +0000",
    "cim": "Raktárvadászok"
  },
  {
    "csatorna": "OZONETV",
    "kezdes": "20260405170000 +0000",
    "vege": "20260405173000 +0000",
    "cim": "Zálogkirályok"
  },
  {
    "csatorna": "OZONETV",
    "kezdes": "20260405173000 +0000",
    "vege": "20260405180000 +0000",
    "cim": "Zálogkirályok"
  },
  {
    "csatorna": "OZONETV",
    "kezdes": "20260405180000 +0000",
    "vege": "20260405183000 +0000",
    "cim": "Zálogkirályok"
  },
  {
    "csatorna": "OZONETV",
    "kezdes": "20260405183000 +0000",
    "vege": "20260405190000 +0000",
    "cim": "Zálogkirályok"
  },
  {
    "csatorna": "OZONETV",
    "kezdes": "20260405190000 +0000",
    "vege": "20260405193000 +0000",
    "cim": "Raktárvadászok"
  },
  {
    "csatorna": "OZONETV",
    "kezdes": "20260405193000 +0000",
    "vege": "20260405200000 +0000",
    "cim": "Raktárvadászok"
  },
  {
    "csatorna": "OZONETV",
    "kezdes": "20260405200000 +0000",
    "vege": "20260405203000 +0000",
    "cim": "Raktárvadászok"
  },
  {
    "csatorna": "OZONETV",
    "kezdes": "20260405203000 +0000",
    "vege": "20260405210000 +0000",
    "cim": "Raktárvadászok"
  },
  {
    "csatorna": "OZONETV",
    "kezdes": "20260405210000 +0000",
    "vege": "20260405213000 +0000",
    "cim": "Raktárvadászok"
  },
  {
    "csatorna": "OZONETV",
    "kezdes": "20260405213000 +0000",
    "vege": "20260405220000 +0000",
    "cim": "Raktárvadászok"
  },
  {
    "csatorna": "OZONETV",
    "kezdes": "20260405220000 +0000",
    "vege": "20260405223000 +0000",
    "cim": "Zálogkirályok"
  },
  {
    "csatorna": "OZONETV",
    "kezdes": "20260405223000 +0000",
    "vege": "20260405230000 +0000",
    "cim": "Zálogkirályok"
  },
  {
    "csatorna": "OZONETV",
    "kezdes": "20260405230000 +0000",
    "vege": "20260405233000 +0000",
    "cim": "Zálogkirályok"
  },
  {
    "csatorna": "OZONETV",
    "kezdes": "20260405233000 +0000",
    "vege": "20260406000000 +0000",
    "cim": "Zálogkirályok"
  },
  {
    "csatorna": "RTL",
    "kezdes": "20260405120000 +0000",
    "vege": "20260405135000 +0000",
    "cim": "Derült égből fasírt"
  },
  {
    "csatorna": "RTL",
    "kezdes": "20260405135000 +0000",
    "vege": "20260405160000 +0000",
    "cim": "Nyúl Péter 2. - Nyúlcipő"
  },
  {
    "csatorna": "RTL",
    "kezdes": "20260405160000 +0000",
    "vege": "20260405165000 +0000",
    "cim": "RTL Híradó - Esti kiadás"
  },
  {
    "csatorna": "RTL",
    "kezdes": "20260405165000 +0000",
    "vege": "20260405175500 +0000",
    "cim": "Házon kívül"
  },
  {
    "csatorna": "RTL",
    "kezdes": "20260405175500 +0000",
    "vege": "20260405200000 +0000",
    "cim": "Aranyhaj és a nagy gubanc"
  },
  {
    "csatorna": "RTL",
    "kezdes": "20260405200000 +0000",
    "vege": "20260405221000 +0000",
    "cim": "Evan, a minden6ó"
  },
  {
    "csatorna": "RTL",
    "kezdes": "20260405221000 +0000",
    "vege": "20260406002500 +0000",
    "cim": "Fél lábbal a paradicsomban"
  },
  {
    "csatorna": "RTL_HAROM",
    "kezdes": "20260405125000 +0000",
    "vege": "20260405151000 +0000",
    "cim": "Az örömapa"
  },
  {
    "csatorna": "RTL_HAROM",
    "kezdes": "20260405151000 +0000",
    "vege": "20260405171500 +0000",
    "cim": "Örömapa 2."
  },
  {
    "csatorna": "RTL_HAROM",
    "kezdes": "20260405171500 +0000",
    "vege": "20260405191500 +0000",
    "cim": "Rendőrakadémia 5.: Irány Miami Beach"
  },
  {
    "csatorna": "RTL_HAROM",
    "kezdes": "20260405191500 +0000",
    "vege": "20260405210000 +0000",
    "cim": "Rendőrakadémia 6.: Az ostromlott város"
  },
  {
    "csatorna": "RTL_HAROM",
    "kezdes": "20260405210000 +0000",
    "vege": "20260405235500 +0000",
    "cim": "Apollo 13"
  },
  {
    "csatorna": "RTL_HAROM",
    "kezdes": "20260405235500 +0000",
    "vege": "20260406031500 +0000",
    "cim": "Végrehajtók"
  },
  {
    "csatorna": "SUPERTV2",
    "kezdes": "20260405132000 +0000",
    "vege": "20260405142500 +0000",
    "cim": "Kincsvadászok"
  },
  {
    "csatorna": "SUPERTV2",
    "kezdes": "20260405142500 +0000",
    "vege": "20260405154000 +0000",
    "cim": "Kincsvadászok"
  },
  {
    "csatorna": "SUPERTV2",
    "kezdes": "20260405154000 +0000",
    "vege": "20260405165000 +0000",
    "cim": "Kincsvadászok"
  },
  {
    "csatorna": "SUPERTV2",
    "kezdes": "20260405165000 +0000",
    "vege": "20260405180000 +0000",
    "cim": "Kincsvadászok"
  },
  {
    "csatorna": "SUPERTV2",
    "kezdes": "20260405180000 +0000",
    "vege": "20260405201500 +0000",
    "cim": "Vadkemping"
  },
  {
    "csatorna": "SUPERTV2",
    "kezdes": "20260405201500 +0000",
    "vege": "20260405221000 +0000",
    "cim": "Stan és Pan"
  },
  {
    "csatorna": "SUPERTV2",
    "kezdes": "20260405221000 +0000",
    "vege": "20260406002500 +0000",
    "cim": "Aszfaltváros"
  },
  {
    "csatorna": "TV2",
    "kezdes": "20260405122500 +0000",
    "vege": "20260405160000 +0000",
    "cim": "A hobbit: Smaug pusztasága"
  },
  {
    "csatorna": "TV2",
    "kezdes": "20260405160000 +0000",
    "vege": "20260405165500 +0000",
    "cim": "Tények"
  },
  {
    "csatorna": "TV2",
    "kezdes": "20260405165500 +0000",
    "vege": "20260405200000 +0000",
    "cim": "A Nagy Duett"
  },
  {
    "csatorna": "TV2",
    "kezdes": "20260405200000 +0000",
    "vege": "20260405223000 +0000",
    "cim": "Magic Mike utolsó tánca"
  },
  {
    "csatorna": "TV2",
    "kezdes": "20260405223000 +0000",
    "vege": "20260406001500 +0000",
    "cim": "Szerelem, angolosan"
  },
  {
    "csatorna": "VIASAT3",
    "kezdes": "20260405121500 +0000",
    "vege": "20260405132000 +0000",
    "cim": "Ide süss! Húsvéti kihívás"
  },
  {
    "csatorna": "VIASAT3",
    "kezdes": "20260405132000 +0000",
    "vege": "20260405142000 +0000",
    "cim": "Ide süss! Húsvéti kihívás"
  },
  {
    "csatorna": "VIASAT3",
    "kezdes": "20260405142000 +0000",
    "vege": "20260405152500 +0000",
    "cim": "Ide süss! Húsvéti kihívás"
  },
  {
    "csatorna": "VIASAT3",
    "kezdes": "20260405152500 +0000",
    "vege": "20260405163000 +0000",
    "cim": "Ide süss! Húsvéti kihívás"
  },
  {
    "csatorna": "VIASAT3",
    "kezdes": "20260405163000 +0000",
    "vege": "20260405190000 +0000",
    "cim": "Kellékfeleség"
  },
  {
    "csatorna": "VIASAT3",
    "kezdes": "20260405190000 +0000",
    "vege": "20260405200500 +0000",
    "cim": "A kegyetlen - Magda Marinko rémtörténete"
  },
  {
    "csatorna": "VIASAT3",
    "kezdes": "20260405200500 +0000",
    "vege": "20260405211000 +0000",
    "cim": "A kegyetlen - Magda Marinko rémtörténete"
  },
  {
    "csatorna": "VIASAT3",
    "kezdes": "20260405211000 +0000",
    "vege": "20260405221000 +0000",
    "cim": "A kegyetlen - Magda Marinko rémtörténete"
  },
  {
    "csatorna": "VIASAT3",
    "kezdes": "20260405221000 +0000",
    "vege": "20260405231000 +0000",
    "cim": "Ide süss! Húsvéti kihívás"
  },
  {
    "csatorna": "VIASAT3",
    "kezdes": "20260405231000 +0000",
    "vege": "20260406001000 +0000",
    "cim": "Ide süss! Húsvéti kihívás"
  },
  {
    "csatorna": "VIASAT6",
    "kezdes": "20260405123500 +0000",
    "vege": "20260405130000 +0000",
    "cim": "A Comedy Central bemutatja"
  },
  {
    "csatorna": "VIASAT6",
    "kezdes": "20260405130000 +0000",
    "vege": "20260405133500 +0000",
    "cim": "A Comedy Central bemutatja"
  },
  {
    "csatorna": "VIASAT6",
    "kezdes": "20260405133500 +0000",
    "vege": "20260405140500 +0000",
    "cim": "A Comedy Central bemutatja"
  },
  {
    "csatorna": "VIASAT6",
    "kezdes": "20260405140500 +0000",
    "vege": "20260405144500 +0000",
    "cim": "A Comedy Central bemutatja"
  },
  {
    "csatorna": "VIASAT6",
    "kezdes": "20260405144500 +0000",
    "vege": "20260405152000 +0000",
    "cim": "A Comedy Central bemutatja"
  },
  {
    "csatorna": "VIASAT6",
    "kezdes": "20260405152000 +0000",
    "vege": "20260405163000 +0000",
    "cim": "A Comedy Central bemutatja"
  },
  {
    "csatorna": "VIASAT6",
    "kezdes": "20260405163000 +0000",
    "vege": "20260405165500 +0000",
    "cim": "A Comedy Central bemutatja"
  },
  {
    "csatorna": "VIASAT6",
    "kezdes": "20260405165500 +0000",
    "vege": "20260405180000 +0000",
    "cim": "Dumaszínház"
  },
  {
    "csatorna": "VIASAT6",
    "kezdes": "20260405180000 +0000",
    "vege": "20260405190500 +0000",
    "cim": "Duma Aktuál"
  },
  {
    "csatorna": "VIASAT6",
    "kezdes": "20260405190500 +0000",
    "vege": "20260405201000 +0000",
    "cim": "Duma Aktuál"
  },
  {
    "csatorna": "VIASAT6",
    "kezdes": "20260405201000 +0000",
    "vege": "20260405203500 +0000",
    "cim": "A Comedy Central bemutatja"
  },
  {
    "csatorna": "VIASAT6",
    "kezdes": "20260405203500 +0000",
    "vege": "20260405210500 +0000",
    "cim": "A Comedy Central bemutatja"
  },
  {
    "csatorna": "VIASAT6",
    "kezdes": "20260405210500 +0000",
    "vege": "20260405213000 +0000",
    "cim": "Tömény történelem"
  },
  {
    "csatorna": "VIASAT6",
    "kezdes": "20260405213000 +0000",
    "vege": "20260405215500 +0000",
    "cim": "Tömény történelem"
  },
  {
    "csatorna": "VIASAT6",
    "kezdes": "20260405215500 +0000",
    "vege": "20260405230000 +0000",
    "cim": "Best of Észbontók"
  },
  {
    "csatorna": "VIASAT6",
    "kezdes": "20260405230000 +0000",
    "vege": "20260405235500 +0000",
    "cim": "Dumaszínház"
  },
  {
    "csatorna": "VIASAT6",
    "kezdes": "20260405235500 +0000",
    "vege": "20260406004000 +0000",
    "cim": "Dumaszínház"
  },
  {
    "csatorna": "VIASAT_FILM",
    "kezdes": "20260405142000 +0000",
    "vege": "20260405161500 +0000",
    "cim": "Poligamy"
  },
  {
    "csatorna": "VIASAT_FILM",
    "kezdes": "20260405161500 +0000",
    "vege": "20260405190000 +0000",
    "cim": "Erin Brockovich - Zűrös természet"
  },
  {
    "csatorna": "VIASAT_FILM",
    "kezdes": "20260405190000 +0000",
    "vege": "20260405211000 +0000",
    "cim": "Úszó erőd"
  },
  {
    "csatorna": "VIASAT_FILM",
    "kezdes": "20260405211000 +0000",
    "vege": "20260405233500 +0000",
    "cim": "A passió"
  },
  {
    "csatorna": "VIASAT_FILM",
    "kezdes": "20260405233500 +0000",
    "vege": "20260406000500 +0000",
    "cim": "Képlet"
  }
]