[
  {
    "csatorna": "AMC",
    "kezdes": "20260327134000 +0000",
    "vege": "20260327160000 +0000",
    "cim": "Pókember"
  },
  {
    "csatorna": "AMC",
    "kezdes": "20260327160000 +0000",
    "vege": "20260327183000 +0000",
    "cim": "Alkonyat - Napfogyatkozás"
  },
  {
    "csatorna": "AMC",
    "kezdes": "20260327183000 +0000",
    "vege": "20260327200000 +0000",
    "cim": "Superhero Movie"
  },
  {
    "csatorna": "AMC",
    "kezdes": "20260327200000 +0000",
    "vege": "20260327215000 +0000",
    "cim": "Kickboxer - Vérbosszú Bangkokban"
  },
  {
    "csatorna": "AMC",
    "kezdes": "20260327215000 +0000",
    "vege": "20260327235000 +0000",
    "cim": "Bérhaverok"
  },
  {
    "csatorna": "AMC",
    "kezdes": "20260327235000 +0000",
    "vege": "20260328013500 +0000",
    "cim": "Az idegen"
  },
  {
    "csatorna": "AXN",
    "kezdes": "20260327121500 +0000",
    "vege": "20260327131000 +0000",
    "cim": "NCIS"
  },
  {
    "csatorna": "AXN",
    "kezdes": "20260327131000 +0000",
    "vege": "20260327141000 +0000",
    "cim": "Smallville"
  },
  {
    "csatorna": "AXN",
    "kezdes": "20260327141000 +0000",
    "vege": "20260327151000 +0000",
    "cim": "Smallville"
  },
  {
    "csatorna": "AXN",
    "kezdes": "20260327151000 +0000",
    "vege": "20260327160500 +0000",
    "cim": "Csillagkapu: Atlantisz"
  },
  {
    "csatorna": "AXN",
    "kezdes": "20260327160500 +0000",
    "vege": "20260327170500 +0000",
    "cim": "Csillagkapu"
  },
  {
    "csatorna": "AXN",
    "kezdes": "20260327170500 +0000",
    "vege": "20260327180000 +0000",
    "cim": "Csillagkapu"
  },
  {
    "csatorna": "AXN",
    "kezdes": "20260327180000 +0000",
    "vege": "20260327190000 +0000",
    "cim": "J.A.G. - Becsületbeli ügyek"
  },
  {
    "csatorna": "AXN",
    "kezdes": "20260327190000 +0000",
    "vege": "20260327200000 +0000",
    "cim": "FBI - New York különleges ügynökei"
  },
  {
    "csatorna": "AXN",
    "kezdes": "20260327200000 +0000",
    "vege": "20260327220500 +0000",
    "cim": "Gothika"
  },
  {
    "csatorna": "AXN",
    "kezdes": "20260327220500 +0000",
    "vege": "20260328001000 +0000",
    "cim": "Életeken át"
  },
  {
    "csatorna": "FILM4",
    "kezdes": "20260327134000 +0000",
    "vege": "20260327152500 +0000",
    "cim": "Még egy tánc"
  },
  {
    "csatorna": "FILM4",
    "kezdes": "20260327152500 +0000",
    "vege": "20260327171500 +0000",
    "cim": "Gyilkos sütik - A karácsonyi puding rejtély (2)"
  },
  {
    "csatorna": "FILM4",
    "kezdes": "20260327171500 +0000",
    "vege": "20260327190000 +0000",
    "cim": "A szívek kikötője"
  },
  {
    "csatorna": "FILM4",
    "kezdes": "20260327190000 +0000",
    "vege": "20260327205000 +0000",
    "cim": "A lopás művészete"
  },
  {
    "csatorna": "FILM4",
    "kezdes": "20260327205000 +0000",
    "vege": "20260327225000 +0000",
    "cim": "Godsend - A teremtés klinikája"
  },
  {
    "csatorna": "FILM4",
    "kezdes": "20260327225000 +0000",
    "vege": "20260328010500 +0000",
    "cim": "Az 54. hadtest"
  },
  {
    "csatorna": "FILMCAFE",
    "kezdes": "20260327120500 +0000",
    "vege": "20260327135000 +0000",
    "cim": "Boldogító igen, vagy nem"
  },
  {
    "csatorna": "FILMCAFE",
    "kezdes": "20260327135000 +0000",
    "vege": "20260327162000 +0000",
    "cim": "Képlet"
  },
  {
    "csatorna": "FILMCAFE",
    "kezdes": "20260327162000 +0000",
    "vege": "20260327180000 +0000",
    "cim": "Jószomszédi iszony"
  },
  {
    "csatorna": "FILMCAFE",
    "kezdes": "20260327180000 +0000",
    "vege": "20260327200000 +0000",
    "cim": "Step Up"
  },
  {
    "csatorna": "FILMCAFE",
    "kezdes": "20260327200000 +0000",
    "vege": "20260327215000 +0000",
    "cim": "Jákob rabbi kalandjai"
  },
  {
    "csatorna": "FILMCAFE",
    "kezdes": "20260327215000 +0000",
    "vege": "20260327235500 +0000",
    "cim": "A bosszú jogán"
  },
  {
    "csatorna": "FILMCAFE",
    "kezdes": "20260327235500 +0000",
    "vege": "20260328020500 +0000",
    "cim": "Ifjúság"
  },
  {
    "csatorna": "FILMMANIA",
    "kezdes": "20260327124000 +0000",
    "vege": "20260327134000 +0000",
    "cim": "Miért nem szóltak Evansnek?"
  },
  {
    "csatorna": "FILMMANIA",
    "kezdes": "20260327134000 +0000",
    "vege": "20260327143500 +0000",
    "cim": "Miért nem szóltak Evansnek?"
  },
  {
    "csatorna": "FILMMANIA",
    "kezdes": "20260327143500 +0000",
    "vege": "20260327153500 +0000",
    "cim": "Miért nem szóltak Evansnek?"
  },
  {
    "csatorna": "FILMMANIA",
    "kezdes": "20260327153500 +0000",
    "vege": "20260327163000 +0000",
    "cim": "Miért nem szóltak Evansnek?"
  },
  {
    "csatorna": "FILMMANIA",
    "kezdes": "20260327163000 +0000",
    "vege": "20260327181000 +0000",
    "cim": "Csapd le Chipet!"
  },
  {
    "csatorna": "FILMMANIA",
    "kezdes": "20260327181000 +0000",
    "vege": "20260327200000 +0000",
    "cim": "Fletch 2. - Szenzációs ajánlat"
  },
  {
    "csatorna": "FILMMANIA",
    "kezdes": "20260327200000 +0000",
    "vege": "20260327220500 +0000",
    "cim": "Piedone Afrikában"
  },
  {
    "csatorna": "FILMMANIA",
    "kezdes": "20260327220500 +0000",
    "vege": "20260328001500 +0000",
    "cim": "Ősharag - Oh-Mah legendája"
  },
  {
    "csatorna": "FILMPLUSSZ",
    "kezdes": "20260327120000 +0000",
    "vege": "20260327140000 +0000",
    "cim": "Egyiptom hercege"
  },
  {
    "csatorna": "FILMPLUSSZ",
    "kezdes": "20260327140000 +0000",
    "vege": "20260327165000 +0000",
    "cim": "Waterworld - Vízivilág"
  },
  {
    "csatorna": "FILMPLUSSZ",
    "kezdes": "20260327165000 +0000",
    "vege": "20260327200000 +0000",
    "cim": "Dűne"
  },
  {
    "csatorna": "FILMPLUSSZ",
    "kezdes": "20260327200000 +0000",
    "vege": "20260327224000 +0000",
    "cim": "Artúr király"
  },
  {
    "csatorna": "FILMPLUSSZ",
    "kezdes": "20260327224000 +0000",
    "vege": "20260328010000 +0000",
    "cim": "Hellboy"
  },
  {
    "csatorna": "MOZIPLUSZ",
    "kezdes": "20260327135000 +0000",
    "vege": "20260327155500 +0000",
    "cim": "Tarzan legendája"
  },
  {
    "csatorna": "MOZIPLUSZ",
    "kezdes": "20260327155500 +0000",
    "vege": "20260327175500 +0000",
    "cim": "Végtelen"
  },
  {
    "csatorna": "MOZIPLUSZ",
    "kezdes": "20260327175500 +0000",
    "vege": "20260327200000 +0000",
    "cim": "Meg - Az őscápa"
  },
  {
    "csatorna": "MOZIPLUSZ",
    "kezdes": "20260327200000 +0000",
    "vege": "20260327222000 +0000",
    "cim": "A kém, aki dobott engem"
  },
  {
    "csatorna": "MOZIPLUSZ",
    "kezdes": "20260327222000 +0000",
    "vege": "20260328002000 +0000",
    "cim": "A sárkány bosszúja 2"
  },
  {
    "csatorna": "MOZIVERZUM",
    "kezdes": "20260327135500 +0000",
    "vege": "20260327160000 +0000",
    "cim": "Fák jú Tanár úr! 2"
  },
  {
    "csatorna": "MOZIVERZUM",
    "kezdes": "20260327160000 +0000",
    "vege": "20260327181000 +0000",
    "cim": "G.I. Joe: A kobra árnyéka"
  },
  {
    "csatorna": "MOZIVERZUM",
    "kezdes": "20260327181000 +0000",
    "vege": "20260327200000 +0000",
    "cim": "Max Payne - Egyszemélyes háború"
  },
  {
    "csatorna": "MOZIVERZUM",
    "kezdes": "20260327200000 +0000",
    "vege": "20260327215500 +0000",
    "cim": "Féktelen harag"
  },
  {
    "csatorna": "MOZIVERZUM",
    "kezdes": "20260327215500 +0000",
    "vege": "20260327234500 +0000",
    "cim": "Gyilkos ösvény"
  },
  {
    "csatorna": "MOZIVERZUM",
    "kezdes": "20260327234500 +0000",
    "vege": "20260328013000 +0000",
    "cim": "Micsoda buli"
  },
  {
    "csatorna": "NICKELODEON",
    "kezdes": "20260327121500 +0000",
    "vege": "20260327123500 +0000",
    "cim": "Wylde-Pak bagázs"
  },
  {
    "csatorna": "NICKELODEON",
    "kezdes": "20260327123500 +0000",
    "vege": "20260327130000 +0000",
    "cim": "SpongyaBob KockaNadrág"
  },
  {
    "csatorna": "NICKELODEON",
    "kezdes": "20260327130000 +0000",
    "vege": "20260327132000 +0000",
    "cim": "Csillag Patrik műsora"
  },
  {
    "csatorna": "NICKELODEON",
    "kezdes": "20260327132000 +0000",
    "vege": "20260327133500 +0000",
    "cim": "Csillag Patrik műsora"
  },
  {
    "csatorna": "NICKELODEON",
    "kezdes": "20260327133500 +0000",
    "vege": "20260327140000 +0000",
    "cim": "A Lármás család"
  },
  {
    "csatorna": "NICKELODEON",
    "kezdes": "20260327140000 +0000",
    "vege": "20260327142000 +0000",
    "cim": "A Lármás család"
  },
  {
    "csatorna": "NICKELODEON",
    "kezdes": "20260327142000 +0000",
    "vege": "20260327144500 +0000",
    "cim": "A Wylde-Pak bagázs"
  },
  {
    "csatorna": "NICKELODEON",
    "kezdes": "20260327144500 +0000",
    "vege": "20260327150500 +0000",
    "cim": "A Wylde-Pak bagázs"
  },
  {
    "csatorna": "NICKELODEON",
    "kezdes": "20260327150500 +0000",
    "vege": "20260327153000 +0000",
    "cim": "SpongyaBob Kockanadrág"
  },
  {
    "csatorna": "NICKELODEON",
    "kezdes": "20260327153000 +0000",
    "vege": "20260327155500 +0000",
    "cim": "A Marsupilamik"
  },
  {
    "csatorna": "NICKELODEON",
    "kezdes": "20260327155500 +0000",
    "vege": "20260327161000 +0000",
    "cim": "A Lármás család"
  },
  {
    "csatorna": "NICKELODEON",
    "kezdes": "20260327161000 +0000",
    "vege": "20260327163000 +0000",
    "cim": "A Lármás család"
  },
  {
    "csatorna": "NICKELODEON",
    "kezdes": "20260327163000 +0000",
    "vege": "20260327165500 +0000",
    "cim": "A Lármás család"
  },
  {
    "csatorna": "NICKELODEON",
    "kezdes": "20260327165500 +0000",
    "vege": "20260327170500 +0000",
    "cim": "A Lármás család"
  },
  {
    "csatorna": "NICKELODEON",
    "kezdes": "20260327170500 +0000",
    "vege": "20260327173000 +0000",
    "cim": "A Thunderman-család: Beépített küldetés"
  },
  {
    "csatorna": "NICKELODEON",
    "kezdes": "20260327173000 +0000",
    "vege": "20260327175500 +0000",
    "cim": "A Thunderman-család: Beépített küldetés"
  },
  {
    "csatorna": "NICKELODEON",
    "kezdes": "20260327175500 +0000",
    "vege": "20260327182000 +0000",
    "cim": "Veszélyes Henry"
  },
  {
    "csatorna": "NICKELODEON",
    "kezdes": "20260327182000 +0000",
    "vege": "20260327184000 +0000",
    "cim": "Veszélyes Henry"
  },
  {
    "csatorna": "NICKELODEON",
    "kezdes": "20260327184000 +0000",
    "vege": "20260327190500 +0000",
    "cim": "Veszélyes Osztag"
  },
  {
    "csatorna": "NICKELODEON",
    "kezdes": "20260327190500 +0000",
    "vege": "20260327193000 +0000",
    "cim": "iCarly"
  },
  {
    "csatorna": "NICKELODEON",
    "kezdes": "20260327193000 +0000",
    "vege": "20260327195000 +0000",
    "cim": "iCarly"
  },
  {
    "csatorna": "NICKELODEON",
    "kezdes": "20260327195000 +0000",
    "vege": "20260327201500 +0000",
    "cim": "V, mint Viktória"
  },
  {
    "csatorna": "NICKELODEON",
    "kezdes": "20260327201500 +0000",
    "vege": "20260327204000 +0000",
    "cim": "Sam és Cat"
  },
  {
    "csatorna": "NICKELODEON",
    "kezdes": "20260327204000 +0000",
    "vege": "20260327210500 +0000",
    "cim": "Mesék a Tini Nindzsa Teknőcökről"
  },
  {
    "csatorna": "NICKELODEON",
    "kezdes": "20260327210500 +0000",
    "vege": "20260327213000 +0000",
    "cim": "Mesék a Tini Nindzsa Teknőcökről"
  },
  {
    "csatorna": "NICKELODEON",
    "kezdes": "20260327213000 +0000",
    "vege": "20260327215000 +0000",
    "cim": "SpongyaBob KockaNadrág"
  },
  {
    "csatorna": "NICKELODEON",
    "kezdes": "20260327215000 +0000",
    "vege": "20260327221500 +0000",
    "cim": "SpongyaBob KockaNadrág"
  },
  {
    "csatorna": "NICKELODEON",
    "kezdes": "20260327221500 +0000",
    "vege": "20260327224000 +0000",
    "cim": "A Marsupilamik"
  },
  {
    "csatorna": "NICKELODEON",
    "kezdes": "20260327224000 +0000",
    "vege": "20260327230000 +0000",
    "cim": "Szipi & Szuper"
  },
  {
    "csatorna": "NICKELODEON",
    "kezdes": "20260327230000 +0000",
    "vege": "20260327232500 +0000",
    "cim": "Szipi & Szuper"
  },
  {
    "csatorna": "NICKELODEON",
    "kezdes": "20260327232500 +0000",
    "vege": "20260327235000 +0000",
    "cim": "Csillag Patrik műsora"
  },
  {
    "csatorna": "NICKELODEON",
    "kezdes": "20260327235000 +0000",
    "vege": "20260328001500 +0000",
    "cim": "Csillag Patrik műsora"
  },
  {
    "csatorna": "OZONETV",
    "kezdes": "20260327120000 +0000",
    "vege": "20260327123000 +0000",
    "cim": "Raktárvadászok"
  },
  {
    "csatorna": "OZONETV",
    "kezdes": "20260327123000 +0000",
    "vege": "20260327130000 +0000",
    "cim": "Raktárvadászok"
  },
  {
    "csatorna": "OZONETV",
    "kezdes": "20260327130000 +0000",
    "vege": "20260327133000 +0000",
    "cim": "Raktárvadászok"
  },
  {
    "csatorna": "OZONETV",
    "kezdes": "20260327133000 +0000",
    "vege": "20260327140000 +0000",
    "cim": "Raktárvadászok"
  },
  {
    "csatorna": "OZONETV",
    "kezdes": "20260327140000 +0000",
    "vege": "20260327143000 +0000",
    "cim": "Zálogcsillagok"
  },
  {
    "csatorna": "OZONETV",
    "kezdes": "20260327143000 +0000",
    "vege": "20260327150000 +0000",
    "cim": "Zálogcsillagok"
  },
  {
    "csatorna": "OZONETV",
    "kezdes": "20260327150000 +0000",
    "vege": "20260327153000 +0000",
    "cim": "Zálogkirályok"
  },
  {
    "csatorna": "OZONETV",
    "kezdes": "20260327153000 +0000",
    "vege": "20260327160000 +0000",
    "cim": "Zálogkirályok"
  },
  {
    "csatorna": "OZONETV",
    "kezdes": "20260327160000 +0000",
    "vege": "20260327170000 +0000",
    "cim": "Tűzben edzett"
  },
  {
    "csatorna": "OZONETV",
    "kezdes": "20260327170000 +0000",
    "vege": "20260327180000 +0000",
    "cim": "Tűzben edzett"
  },
  {
    "csatorna": "OZONETV",
    "kezdes": "20260327180000 +0000",
    "vege": "20260327183000 +0000",
    "cim": "Raktárvadászok"
  },
  {
    "csatorna": "OZONETV",
    "kezdes": "20260327183000 +0000",
    "vege": "20260327190000 +0000",
    "cim": "Raktárvadászok"
  },
  {
    "csatorna": "OZONETV",
    "kezdes": "20260327190000 +0000",
    "vege": "20260327193000 +0000",
    "cim": "Raktárvadászok"
  },
  {
    "csatorna": "OZONETV",
    "kezdes": "20260327193000 +0000",
    "vege": "20260327200000 +0000",
    "cim": "Raktárvadászok"
  },
  {
    "csatorna": "OZONETV",
    "kezdes": "20260327200000 +0000",
    "vege": "20260327203000 +0000",
    "cim": "Texasi raktárvadászok"
  },
  {
    "csatorna": "OZONETV",
    "kezdes": "20260327203000 +0000",
    "vege": "20260327210000 +0000",
    "cim": "Texasi raktárvadászok"
  },
  {
    "csatorna": "OZONETV",
    "kezdes": "20260327210000 +0000",
    "vege": "20260327213000 +0000",
    "cim": "Texasi raktárvadászok"
  },
  {
    "csatorna": "OZONETV",
    "kezdes": "20260327213000 +0000",
    "vege": "20260327220000 +0000",
    "cim": "Texasi raktárvadászok"
  },
  {
    "csatorna": "OZONETV",
    "kezdes": "20260327220000 +0000",
    "vege": "20260327230000 +0000",
    "cim": "Tűzben edzett"
  },
  {
    "csatorna": "OZONETV",
    "kezdes": "20260327230000 +0000",
    "vege": "20260327233000 +0000",
    "cim": "Hogyan készül? Megmutatjuk!"
  },
  {
    "csatorna": "OZONETV",
    "kezdes": "20260327233000 +0000",
    "vege": "20260328000000 +0000",
    "cim": "Hogyan készül? Megmutatjuk!"
  },
  {
    "csatorna": "RTL",
    "kezdes": "20260327120000 +0000",
    "vege": "20260327123500 +0000",
    "cim": "RTL Híradó 1 órakor"
  },
  {
    "csatorna": "RTL",
    "kezdes": "20260327123500 +0000",
    "vege": "20260327135000 +0000",
    "cim": "Dr. House"
  },
  {
    "csatorna": "RTL",
    "kezdes": "20260327135000 +0000",
    "vege": "20260327142500 +0000",
    "cim": "Barátok közt"
  },
  {
    "csatorna": "RTL",
    "kezdes": "20260327142500 +0000",
    "vege": "20260327153000 +0000",
    "cim": "Castle"
  },
  {
    "csatorna": "RTL",
    "kezdes": "20260327153000 +0000",
    "vege": "20260327170000 +0000",
    "cim": "Drága örökösök - A visszatérés"
  },
  {
    "csatorna": "RTL",
    "kezdes": "20260327170000 +0000",
    "vege": "20260327175500 +0000",
    "cim": "RTL Híradó - Esti kiadás"
  },
  {
    "csatorna": "RTL",
    "kezdes": "20260327175500 +0000",
    "vege": "20260327185500 +0000",
    "cim": "Fókusz"
  },
  {
    "csatorna": "RTL",
    "kezdes": "20260327185500 +0000",
    "vege": "20260327200500 +0000",
    "cim": "Pokoli rokonok"
  },
  {
    "csatorna": "RTL",
    "kezdes": "20260327200500 +0000",
    "vege": "20260327212000 +0000",
    "cim": "Apatigris"
  },
  {
    "csatorna": "RTL",
    "kezdes": "20260327212000 +0000",
    "vege": "20260327215500 +0000",
    "cim": "RTL Híradó - Késő esti kiadás"
  },
  {
    "csatorna": "RTL",
    "kezdes": "20260327215500 +0000",
    "vege": "20260328000500 +0000",
    "cim": "Tango és Cash"
  },
  {
    "csatorna": "RTL_HAROM",
    "kezdes": "20260327131500 +0000",
    "vege": "20260327153000 +0000",
    "cim": "Tökéletes hang"
  },
  {
    "csatorna": "RTL_HAROM",
    "kezdes": "20260327153000 +0000",
    "vege": "20260327173000 +0000",
    "cim": "A házinyuszi"
  },
  {
    "csatorna": "RTL_HAROM",
    "kezdes": "20260327173000 +0000",
    "vege": "20260327200000 +0000",
    "cim": "Everest"
  },
  {
    "csatorna": "RTL_HAROM",
    "kezdes": "20260327200000 +0000",
    "vege": "20260327222000 +0000",
    "cim": "Ex Machina"
  },
  {
    "csatorna": "RTL_HAROM",
    "kezdes": "20260327222000 +0000",
    "vege": "20260328003000 +0000",
    "cim": "Ragadozó 2."
  },
  {
    "csatorna": "SUPERTV2",
    "kezdes": "20260327121500 +0000",
    "vege": "20260327131500 +0000",
    "cim": "Családi titkok"
  },
  {
    "csatorna": "SUPERTV2",
    "kezdes": "20260327131500 +0000",
    "vege": "20260327145000 +0000",
    "cim": "Kincsvadászok"
  },
  {
    "csatorna": "SUPERTV2",
    "kezdes": "20260327145000 +0000",
    "vege": "20260327152000 +0000",
    "cim": "STV2 Tények 2026"
  },
  {
    "csatorna": "SUPERTV2",
    "kezdes": "20260327152000 +0000",
    "vege": "20260327155500 +0000",
    "cim": "Csapdába csalva"
  },
  {
    "csatorna": "SUPERTV2",
    "kezdes": "20260327155500 +0000",
    "vege": "20260327180000 +0000",
    "cim": "Exatlon Hungary"
  },
  {
    "csatorna": "SUPERTV2",
    "kezdes": "20260327180000 +0000",
    "vege": "20260327190000 +0000",
    "cim": "Újratervezés"
  },
  {
    "csatorna": "SUPERTV2",
    "kezdes": "20260327190000 +0000",
    "vege": "20260327201500 +0000",
    "cim": "Hal a tortán"
  },
  {
    "csatorna": "SUPERTV2",
    "kezdes": "20260327201500 +0000",
    "vege": "20260327215000 +0000",
    "cim": "Kincsvadászok"
  },
  {
    "csatorna": "SUPERTV2",
    "kezdes": "20260327215000 +0000",
    "vege": "20260327233500 +0000",
    "cim": "A hónap dolgozója"
  },
  {
    "csatorna": "SUPERTV2",
    "kezdes": "20260327233500 +0000",
    "vege": "20260328003500 +0000",
    "cim": "Magánnyomozók"
  },
  {
    "csatorna": "TV2",
    "kezdes": "20260327121500 +0000",
    "vege": "20260327132500 +0000",
    "cim": "Walker, a texasi kopó"
  },
  {
    "csatorna": "TV2",
    "kezdes": "20260327132500 +0000",
    "vege": "20260327143500 +0000",
    "cim": "Aurora angyala"
  },
  {
    "csatorna": "TV2",
    "kezdes": "20260327143500 +0000",
    "vege": "20260327154000 +0000",
    "cim": "Isztambuli árvák"
  },
  {
    "csatorna": "TV2",
    "kezdes": "20260327154000 +0000",
    "vege": "20260327170000 +0000",
    "cim": "Távoli város"
  },
  {
    "csatorna": "TV2",
    "kezdes": "20260327170000 +0000",
    "vege": "20260327174500 +0000",
    "cim": "Tények"
  },
  {
    "csatorna": "TV2",
    "kezdes": "20260327174500 +0000",
    "vege": "20260327190000 +0000",
    "cim": "Tények Plusz"
  },
  {
    "csatorna": "TV2",
    "kezdes": "20260327190000 +0000",
    "vege": "20260327220000 +0000",
    "cim": "Exatlon Hungary"
  },
  {
    "csatorna": "TV2",
    "kezdes": "20260327220000 +0000",
    "vege": "20260327231500 +0000",
    "cim": "Újratervezés"
  },
  {
    "csatorna": "TV2",
    "kezdes": "20260327231500 +0000",
    "vege": "20260327235000 +0000",
    "cim": "Tények extra"
  },
  {
    "csatorna": "TV2",
    "kezdes": "20260327235000 +0000",
    "vege": "20260328005000 +0000",
    "cim": "NCIS: Sydney"
  },
  {
    "csatorna": "VIASAT3",
    "kezdes": "20260327121500 +0000",
    "vege": "20260327131500 +0000",
    "cim": "Beverly Hills 90210"
  },
  {
    "csatorna": "VIASAT3",
    "kezdes": "20260327131500 +0000",
    "vege": "20260327141500 +0000",
    "cim": "Szívek szállodája"
  },
  {
    "csatorna": "VIASAT3",
    "kezdes": "20260327141500 +0000",
    "vege": "20260327151500 +0000",
    "cim": "Szívek szállodája"
  },
  {
    "csatorna": "VIASAT3",
    "kezdes": "20260327151500 +0000",
    "vege": "20260327160500 +0000",
    "cim": "A Grace klinika"
  },
  {
    "csatorna": "VIASAT3",
    "kezdes": "20260327160500 +0000",
    "vege": "20260327170000 +0000",
    "cim": "A Grace klinika"
  },
  {
    "csatorna": "VIASAT3",
    "kezdes": "20260327170000 +0000",
    "vege": "20260327180000 +0000",
    "cim": "A Grace klinika"
  },
  {
    "csatorna": "VIASAT3",
    "kezdes": "20260327180000 +0000",
    "vege": "20260327190500 +0000",
    "cim": "Dumaszínház"
  },
  {
    "csatorna": "VIASAT3",
    "kezdes": "20260327190500 +0000",
    "vege": "20260327195500 +0000",
    "cim": "Dumaszínház"
  },
  {
    "csatorna": "VIASAT3",
    "kezdes": "20260327195500 +0000",
    "vege": "20260327210000 +0000",
    "cim": "Dumaszínház"
  },
  {
    "csatorna": "VIASAT3",
    "kezdes": "20260327210000 +0000",
    "vege": "20260327220500 +0000",
    "cim": "Cyla Call Center"
  },
  {
    "csatorna": "VIASAT3",
    "kezdes": "20260327220500 +0000",
    "vege": "20260327230500 +0000",
    "cim": "Pop, kaja satöbbi"
  },
  {
    "csatorna": "VIASAT3",
    "kezdes": "20260327230500 +0000",
    "vege": "20260328000500 +0000",
    "cim": "A Grace klinika"
  },
  {
    "csatorna": "VIASAT6",
    "kezdes": "20260327125000 +0000",
    "vege": "20260327135000 +0000",
    "cim": "Duma Aktuál"
  },
  {
    "csatorna": "VIASAT6",
    "kezdes": "20260327135000 +0000",
    "vege": "20260327145000 +0000",
    "cim": "Dumaszínház"
  },
  {
    "csatorna": "VIASAT6",
    "kezdes": "20260327145000 +0000",
    "vege": "20260327152000 +0000",
    "cim": "A Comedy Central bemutatja"
  },
  {
    "csatorna": "VIASAT6",
    "kezdes": "20260327152000 +0000",
    "vege": "20260327155500 +0000",
    "cim": "A Comedy Central bemutatja"
  },
  {
    "csatorna": "VIASAT6",
    "kezdes": "20260327155500 +0000",
    "vege": "20260327165500 +0000",
    "cim": "Észbontók"
  },
  {
    "csatorna": "VIASAT6",
    "kezdes": "20260327165500 +0000",
    "vege": "20260327180000 +0000",
    "cim": "Észbontók"
  },
  {
    "csatorna": "VIASAT6",
    "kezdes": "20260327180000 +0000",
    "vege": "20260327190000 +0000",
    "cim": "KAPóra"
  },
  {
    "csatorna": "VIASAT6",
    "kezdes": "20260327190000 +0000",
    "vege": "20260327200000 +0000",
    "cim": "KAPóra"
  },
  {
    "csatorna": "VIASAT6",
    "kezdes": "20260327200000 +0000",
    "vege": "20260327213000 +0000",
    "cim": "Dumaszínház"
  },
  {
    "csatorna": "VIASAT6",
    "kezdes": "20260327213000 +0000",
    "vege": "20260327220000 +0000",
    "cim": "A Comedy Central bemutatja"
  },
  {
    "csatorna": "VIASAT6",
    "kezdes": "20260327220000 +0000",
    "vege": "20260327223000 +0000",
    "cim": "A Comedy Central bemutatja"
  },
  {
    "csatorna": "VIASAT6",
    "kezdes": "20260327223000 +0000",
    "vege": "20260327233500 +0000",
    "cim": "Mogács Dániel: Bolondok Hajója"
  },
  {
    "csatorna": "VIASAT6",
    "kezdes": "20260327233500 +0000",
    "vege": "20260328003500 +0000",
    "cim": "Duma Aktuál"
  },
  {
    "csatorna": "VIASAT_FILM",
    "kezdes": "20260327134000 +0000",
    "vege": "20260327152500 +0000",
    "cim": "Hupikék törpikék - Az elveszett falu"
  },
  {
    "csatorna": "VIASAT_FILM",
    "kezdes": "20260327152500 +0000",
    "vege": "20260327174500 +0000",
    "cim": "A három testőr"
  },
  {
    "csatorna": "VIASAT_FILM",
    "kezdes": "20260327174500 +0000",
    "vege": "20260327200000 +0000",
    "cim": "Gumiláb"
  },
  {
    "csatorna": "VIASAT_FILM",
    "kezdes": "20260327200000 +0000",
    "vege": "20260327221000 +0000",
    "cim": "Szex a lelke mindennek"
  },
  {
    "csatorna": "VIASAT_FILM",
    "kezdes": "20260327221000 +0000",
    "vege": "20260328001000 +0000",
    "cim": "Miután boldogok leszünk"
  }
]