[
  {
    "csatorna": "AMC",
    "kezdes": "20260406135500 +0000",
    "vege": "20260406170000 +0000",
    "cim": 2012
  },
  {
    "csatorna": "AMC",
    "kezdes": "20260406170000 +0000",
    "vege": "20260406190000 +0000",
    "cim": "Percy Jackson - Szörnyek tengere"
  },
  {
    "csatorna": "AMC",
    "kezdes": "20260406190000 +0000",
    "vege": "20260406204000 +0000",
    "cim": "Taxi"
  },
  {
    "csatorna": "AMC",
    "kezdes": "20260406204000 +0000",
    "vege": "20260406224000 +0000",
    "cim": "Hiába futsz"
  },
  {
    "csatorna": "AMC",
    "kezdes": "20260406224000 +0000",
    "vege": "20260407004500 +0000",
    "cim": "X-akták: A film"
  },
  {
    "csatorna": "AXN",
    "kezdes": "20260406125500 +0000",
    "vege": "20260406135500 +0000",
    "cim": "Csillagkapu: Atlantisz"
  },
  {
    "csatorna": "AXN",
    "kezdes": "20260406135500 +0000",
    "vege": "20260406145500 +0000",
    "cim": "Csillagkapu: Atlantisz"
  },
  {
    "csatorna": "AXN",
    "kezdes": "20260406145500 +0000",
    "vege": "20260406155500 +0000",
    "cim": "Csillagkapu"
  },
  {
    "csatorna": "AXN",
    "kezdes": "20260406155500 +0000",
    "vege": "20260406170000 +0000",
    "cim": "Csillagkapu"
  },
  {
    "csatorna": "AXN",
    "kezdes": "20260406170000 +0000",
    "vege": "20260406180000 +0000",
    "cim": "J.A.G. - Becsületbeli ügyek"
  },
  {
    "csatorna": "AXN",
    "kezdes": "20260406180000 +0000",
    "vege": "20260406190000 +0000",
    "cim": "FBI - New York különleges ügynökei"
  },
  {
    "csatorna": "AXN",
    "kezdes": "20260406190000 +0000",
    "vege": "20260406200000 +0000",
    "cim": "Az elveszett világ"
  },
  {
    "csatorna": "AXN",
    "kezdes": "20260406200000 +0000",
    "vege": "20260406210000 +0000",
    "cim": "Az elveszett jelkép"
  },
  {
    "csatorna": "AXN",
    "kezdes": "20260406210000 +0000",
    "vege": "20260406225500 +0000",
    "cim": "A cipőbűvölő"
  },
  {
    "csatorna": "AXN",
    "kezdes": "20260406225500 +0000",
    "vege": "20260406235000 +0000",
    "cim": "J.A.G. - Becsületbeli ügyek"
  },
  {
    "csatorna": "AXN",
    "kezdes": "20260406235000 +0000",
    "vege": "20260407003000 +0000",
    "cim": "NCIS XX."
  },
  {
    "csatorna": "FILM4",
    "kezdes": "20260406124000 +0000",
    "vege": "20260406143500 +0000",
    "cim": "Kis hazugságok a szerelem nevében"
  },
  {
    "csatorna": "FILM4",
    "kezdes": "20260406143500 +0000",
    "vege": "20260406161500 +0000",
    "cim": "Ármányos manipulációk"
  },
  {
    "csatorna": "FILM4",
    "kezdes": "20260406161500 +0000",
    "vege": "20260406180000 +0000",
    "cim": "Lesz ez még jobb"
  },
  {
    "csatorna": "FILM4",
    "kezdes": "20260406180000 +0000",
    "vege": "20260406201000 +0000",
    "cim": "A panamai szabó"
  },
  {
    "csatorna": "FILM4",
    "kezdes": "20260406201000 +0000",
    "vege": "20260406225500 +0000",
    "cim": "Traffic"
  },
  {
    "csatorna": "FILM4",
    "kezdes": "20260406225500 +0000",
    "vege": "20260407004500 +0000",
    "cim": "Hudson Hawk - Egy mestertolvaj aranyat ér"
  },
  {
    "csatorna": "FILMCAFE",
    "kezdes": "20260406130000 +0000",
    "vege": "20260406150500 +0000",
    "cim": "Fura farm"
  },
  {
    "csatorna": "FILMCAFE",
    "kezdes": "20260406150500 +0000",
    "vege": "20260406170500 +0000",
    "cim": "Gyalog Galopp"
  },
  {
    "csatorna": "FILMCAFE",
    "kezdes": "20260406170500 +0000",
    "vege": "20260406190000 +0000",
    "cim": "Sejtcserés támadás"
  },
  {
    "csatorna": "FILMCAFE",
    "kezdes": "20260406190000 +0000",
    "vege": "20260406211500 +0000",
    "cim": "Jumanji - A következő szint"
  },
  {
    "csatorna": "FILMCAFE",
    "kezdes": "20260406211500 +0000",
    "vege": "20260406231500 +0000",
    "cim": "Holtak hajnala"
  },
  {
    "csatorna": "FILMCAFE",
    "kezdes": "20260406231500 +0000",
    "vege": "20260407004500 +0000",
    "cim": "Kígyófej"
  },
  {
    "csatorna": "FILMMANIA",
    "kezdes": "20260406121500 +0000",
    "vege": "20260406141500 +0000",
    "cim": "Jackie Chan: Városi vadász"
  },
  {
    "csatorna": "FILMMANIA",
    "kezdes": "20260406141500 +0000",
    "vege": "20260406170500 +0000",
    "cim": "Atomcsapda"
  },
  {
    "csatorna": "FILMMANIA",
    "kezdes": "20260406170500 +0000",
    "vege": "20260406190000 +0000",
    "cim": "Rendőrsztori"
  },
  {
    "csatorna": "FILMMANIA",
    "kezdes": "20260406190000 +0000",
    "vege": "20260406203500 +0000",
    "cim": "Rambo"
  },
  {
    "csatorna": "FILMMANIA",
    "kezdes": "20260406203500 +0000",
    "vege": "20260406222000 +0000",
    "cim": "A nagy fehér"
  },
  {
    "csatorna": "FILMMANIA",
    "kezdes": "20260406222000 +0000",
    "vege": "20260407002500 +0000",
    "cim": "Alvilági játékok"
  },
  {
    "csatorna": "FILMPLUSSZ",
    "kezdes": "20260406122500 +0000",
    "vege": "20260406142500 +0000",
    "cim": "Nagypapa hadművelet"
  },
  {
    "csatorna": "FILMPLUSSZ",
    "kezdes": "20260406142500 +0000",
    "vege": "20260406162000 +0000",
    "cim": "Vén csontok"
  },
  {
    "csatorna": "FILMPLUSSZ",
    "kezdes": "20260406162000 +0000",
    "vege": "20260406190000 +0000",
    "cim": "Halálos iramban: Hobbs & Shaw"
  },
  {
    "csatorna": "FILMPLUSSZ",
    "kezdes": "20260406190000 +0000",
    "vege": "20260406210000 +0000",
    "cim": "Die Hard - Drágább, mint az életed"
  },
  {
    "csatorna": "FILMPLUSSZ",
    "kezdes": "20260406210000 +0000",
    "vege": "20260406232500 +0000",
    "cim": "Looper - A jövő gyilkosa"
  },
  {
    "csatorna": "FILMPLUSSZ",
    "kezdes": "20260406232500 +0000",
    "vege": "20260407033000 +0000",
    "cim": "Hét nővér"
  },
  {
    "csatorna": "MOZIPLUSZ",
    "kezdes": "20260406122000 +0000",
    "vege": "20260406142000 +0000",
    "cim": "A Múmia - A Sárkánycsászár sírja"
  },
  {
    "csatorna": "MOZIPLUSZ",
    "kezdes": "20260406142000 +0000",
    "vege": "20260406163000 +0000",
    "cim": "Jurassic World"
  },
  {
    "csatorna": "MOZIPLUSZ",
    "kezdes": "20260406163000 +0000",
    "vege": "20260406190000 +0000",
    "cim": "Die Hard 4.0: Legdrágább az életed"
  },
  {
    "csatorna": "MOZIPLUSZ",
    "kezdes": "20260406190000 +0000",
    "vege": "20260406211000 +0000",
    "cim": "Bad Boys - Mindent vagy többet"
  },
  {
    "csatorna": "MOZIPLUSZ",
    "kezdes": "20260406211000 +0000",
    "vege": "20260406225500 +0000",
    "cim": "Háború mindenki ellen"
  },
  {
    "csatorna": "MOZIPLUSZ",
    "kezdes": "20260406225500 +0000",
    "vege": "20260407005000 +0000",
    "cim": "A specialista"
  },
  {
    "csatorna": "MOZIVERZUM",
    "kezdes": "20260406120000 +0000",
    "vege": "20260406135500 +0000",
    "cim": "Addams Family - A galád család"
  },
  {
    "csatorna": "MOZIVERZUM",
    "kezdes": "20260406135500 +0000",
    "vege": "20260406154000 +0000",
    "cim": "Addams Family 2. - Egy kicsivel galádabb a család"
  },
  {
    "csatorna": "MOZIVERZUM",
    "kezdes": "20260406154000 +0000",
    "vege": "20260406172500 +0000",
    "cim": "Lassie hazatér"
  },
  {
    "csatorna": "MOZIVERZUM",
    "kezdes": "20260406172500 +0000",
    "vege": "20260406190000 +0000",
    "cim": "Kiskedvencek elszabadulva"
  },
  {
    "csatorna": "MOZIVERZUM",
    "kezdes": "20260406190000 +0000",
    "vege": "20260406211000 +0000",
    "cim": "Zöld darázs"
  },
  {
    "csatorna": "MOZIVERZUM",
    "kezdes": "20260406211000 +0000",
    "vege": "20260407002500 +0000",
    "cim": "A Wall Street farkasa"
  },
  {
    "csatorna": "NICKELODEON",
    "kezdes": "20260406120000 +0000",
    "vege": "20260406121500 +0000",
    "cim": "A Lármás család"
  },
  {
    "csatorna": "NICKELODEON",
    "kezdes": "20260406121500 +0000",
    "vege": "20260406122500 +0000",
    "cim": "Wylde Pak"
  },
  {
    "csatorna": "NICKELODEON",
    "kezdes": "20260406122500 +0000",
    "vege": "20260406124000 +0000",
    "cim": "Wylde Pak"
  },
  {
    "csatorna": "NICKELODEON",
    "kezdes": "20260406124000 +0000",
    "vege": "20260406130000 +0000",
    "cim": "Wylde-Pak bagázs"
  },
  {
    "csatorna": "NICKELODEON",
    "kezdes": "20260406130000 +0000",
    "vege": "20260406132500 +0000",
    "cim": "SpongyaBob Kockanadrág"
  },
  {
    "csatorna": "NICKELODEON",
    "kezdes": "20260406132500 +0000",
    "vege": "20260406135000 +0000",
    "cim": "A Marsupilamik"
  },
  {
    "csatorna": "NICKELODEON",
    "kezdes": "20260406135000 +0000",
    "vege": "20260406140000 +0000",
    "cim": "A Lármás család"
  },
  {
    "csatorna": "NICKELODEON",
    "kezdes": "20260406140000 +0000",
    "vege": "20260406142500 +0000",
    "cim": "A Lármás család"
  },
  {
    "csatorna": "NICKELODEON",
    "kezdes": "20260406142500 +0000",
    "vege": "20260406145000 +0000",
    "cim": "A Lármás család"
  },
  {
    "csatorna": "NICKELODEON",
    "kezdes": "20260406145000 +0000",
    "vege": "20260406150000 +0000",
    "cim": "A Lármás család"
  },
  {
    "csatorna": "NICKELODEON",
    "kezdes": "20260406150000 +0000",
    "vege": "20260406152500 +0000",
    "cim": "That Girl Lay Lay"
  },
  {
    "csatorna": "NICKELODEON",
    "kezdes": "20260406152500 +0000",
    "vege": "20260406154500 +0000",
    "cim": "A Thunderman-család: Beépített küldetés"
  },
  {
    "csatorna": "NICKELODEON",
    "kezdes": "20260406154500 +0000",
    "vege": "20260406161000 +0000",
    "cim": "Veszélyes Henry"
  },
  {
    "csatorna": "NICKELODEON",
    "kezdes": "20260406161000 +0000",
    "vege": "20260406163500 +0000",
    "cim": "Veszélyes Henry"
  },
  {
    "csatorna": "NICKELODEON",
    "kezdes": "20260406163500 +0000",
    "vege": "20260406165500 +0000",
    "cim": "Veszélyes Osztag"
  },
  {
    "csatorna": "NICKELODEON",
    "kezdes": "20260406165500 +0000",
    "vege": "20260406172000 +0000",
    "cim": "iCarly"
  },
  {
    "csatorna": "NICKELODEON",
    "kezdes": "20260406172000 +0000",
    "vege": "20260406174500 +0000",
    "cim": "iCarly"
  },
  {
    "csatorna": "NICKELODEON",
    "kezdes": "20260406174500 +0000",
    "vege": "20260406181000 +0000",
    "cim": "V, mint Viktória"
  },
  {
    "csatorna": "NICKELODEON",
    "kezdes": "20260406181000 +0000",
    "vege": "20260406183500 +0000",
    "cim": "Sam és Cat"
  },
  {
    "csatorna": "NICKELODEON",
    "kezdes": "20260406183500 +0000",
    "vege": "20260406185500 +0000",
    "cim": "Mesék a Tini Nindzsa Teknőcökről"
  },
  {
    "csatorna": "NICKELODEON",
    "kezdes": "20260406185500 +0000",
    "vege": "20260406192000 +0000",
    "cim": "Mesék a Tini Nindzsa Teknőcökről"
  },
  {
    "csatorna": "NICKELODEON",
    "kezdes": "20260406192000 +0000",
    "vege": "20260406194500 +0000",
    "cim": "SpongyaBob KockaNadrág"
  },
  {
    "csatorna": "NICKELODEON",
    "kezdes": "20260406194500 +0000",
    "vege": "20260406201000 +0000",
    "cim": "SpongyaBob KockaNadrág"
  },
  {
    "csatorna": "NICKELODEON",
    "kezdes": "20260406201000 +0000",
    "vege": "20260406203000 +0000",
    "cim": "A Marsupilamik"
  },
  {
    "csatorna": "NICKELODEON",
    "kezdes": "20260406203000 +0000",
    "vege": "20260406205500 +0000",
    "cim": "Szipi & Szuper"
  },
  {
    "csatorna": "NICKELODEON",
    "kezdes": "20260406205500 +0000",
    "vege": "20260406211500 +0000",
    "cim": "Szipi & Szuper"
  },
  {
    "csatorna": "NICKELODEON",
    "kezdes": "20260406211500 +0000",
    "vege": "20260406214000 +0000",
    "cim": "Csillag Patrik műsora"
  },
  {
    "csatorna": "NICKELODEON",
    "kezdes": "20260406214000 +0000",
    "vege": "20260406220500 +0000",
    "cim": "Csillag Patrik műsora"
  },
  {
    "csatorna": "NICKELODEON",
    "kezdes": "20260406220500 +0000",
    "vege": "20260406222500 +0000",
    "cim": "SpongyaBob KockaNadrág"
  },
  {
    "csatorna": "NICKELODEON",
    "kezdes": "20260406222500 +0000",
    "vege": "20260406224000 +0000",
    "cim": "SpongyaBob KockaNadrág"
  },
  {
    "csatorna": "NICKELODEON",
    "kezdes": "20260406224000 +0000",
    "vege": "20260406230500 +0000",
    "cim": "A Thunderman-család: Beépített küldetés"
  },
  {
    "csatorna": "NICKELODEON",
    "kezdes": "20260406230500 +0000",
    "vege": "20260406233000 +0000",
    "cim": "Veszélyes Osztag"
  },
  {
    "csatorna": "NICKELODEON",
    "kezdes": "20260406233000 +0000",
    "vege": "20260406235000 +0000",
    "cim": "Veszélyes Henry"
  },
  {
    "csatorna": "NICKELODEON",
    "kezdes": "20260406235000 +0000",
    "vege": "20260407002000 +0000",
    "cim": "A Lármás család"
  },
  {
    "csatorna": "OZONETV",
    "kezdes": "20260406120000 +0000",
    "vege": "20260406123000 +0000",
    "cim": "Raktárvadászok"
  },
  {
    "csatorna": "OZONETV",
    "kezdes": "20260406123000 +0000",
    "vege": "20260406130000 +0000",
    "cim": "Raktárvadászok"
  },
  {
    "csatorna": "OZONETV",
    "kezdes": "20260406130000 +0000",
    "vege": "20260406133000 +0000",
    "cim": "Zálogcsillagok"
  },
  {
    "csatorna": "OZONETV",
    "kezdes": "20260406133000 +0000",
    "vege": "20260406140000 +0000",
    "cim": "Zálogcsillagok"
  },
  {
    "csatorna": "OZONETV",
    "kezdes": "20260406140000 +0000",
    "vege": "20260406143000 +0000",
    "cim": "Zálogkirályok"
  },
  {
    "csatorna": "OZONETV",
    "kezdes": "20260406143000 +0000",
    "vege": "20260406150000 +0000",
    "cim": "Zálogkirályok"
  },
  {
    "csatorna": "OZONETV",
    "kezdes": "20260406150000 +0000",
    "vege": "20260406160000 +0000",
    "cim": "Tűzben edzett"
  },
  {
    "csatorna": "OZONETV",
    "kezdes": "20260406160000 +0000",
    "vege": "20260406170000 +0000",
    "cim": "Tűzben edzett"
  },
  {
    "csatorna": "OZONETV",
    "kezdes": "20260406170000 +0000",
    "vege": "20260406173000 +0000",
    "cim": "Raktárvadászok"
  },
  {
    "csatorna": "OZONETV",
    "kezdes": "20260406173000 +0000",
    "vege": "20260406180000 +0000",
    "cim": "Raktárvadászok"
  },
  {
    "csatorna": "OZONETV",
    "kezdes": "20260406180000 +0000",
    "vege": "20260406183000 +0000",
    "cim": "Raktárvadászok"
  },
  {
    "csatorna": "OZONETV",
    "kezdes": "20260406183000 +0000",
    "vege": "20260406190000 +0000",
    "cim": "Raktárvadászok"
  },
  {
    "csatorna": "OZONETV",
    "kezdes": "20260406190000 +0000",
    "vege": "20260406193000 +0000",
    "cim": "Texasi raktárvadászok"
  },
  {
    "csatorna": "OZONETV",
    "kezdes": "20260406193000 +0000",
    "vege": "20260406200000 +0000",
    "cim": "Texasi raktárvadászok"
  },
  {
    "csatorna": "OZONETV",
    "kezdes": "20260406200000 +0000",
    "vege": "20260406203000 +0000",
    "cim": "Texasi raktárvadászok"
  },
  {
    "csatorna": "OZONETV",
    "kezdes": "20260406203000 +0000",
    "vege": "20260406210000 +0000",
    "cim": "Texasi raktárvadászok"
  },
  {
    "csatorna": "OZONETV",
    "kezdes": "20260406210000 +0000",
    "vege": "20260406220000 +0000",
    "cim": "Tűzben edzett"
  },
  {
    "csatorna": "OZONETV",
    "kezdes": "20260406220000 +0000",
    "vege": "20260406223000 +0000",
    "cim": "Hogyan készül? Megmutatjuk!"
  },
  {
    "csatorna": "OZONETV",
    "kezdes": "20260406223000 +0000",
    "vege": "20260406230000 +0000",
    "cim": "Hogyan készül? Megmutatjuk!"
  },
  {
    "csatorna": "OZONETV",
    "kezdes": "20260406230000 +0000",
    "vege": "20260406233000 +0000",
    "cim": "Hogyan készül? Megmutatjuk!"
  },
  {
    "csatorna": "OZONETV",
    "kezdes": "20260406233000 +0000",
    "vege": "20260407000000 +0000",
    "cim": "Hogyan készül? Megmutatjuk!"
  },
  {
    "csatorna": "RTL",
    "kezdes": "20260406131500 +0000",
    "vege": "20260406160000 +0000",
    "cim": "Neveletlen hercegnő"
  },
  {
    "csatorna": "RTL",
    "kezdes": "20260406160000 +0000",
    "vege": "20260406170000 +0000",
    "cim": "RTL Híradó - Esti kiadás"
  },
  {
    "csatorna": "RTL",
    "kezdes": "20260406170000 +0000",
    "vege": "20260406190000 +0000",
    "cim": "Kívánság"
  },
  {
    "csatorna": "RTL",
    "kezdes": "20260406190000 +0000",
    "vege": "20260406215000 +0000",
    "cim": "Aladdin"
  },
  {
    "csatorna": "RTL",
    "kezdes": "20260406215000 +0000",
    "vege": "20260407000000 +0000",
    "cim": "Együtt kezdtük"
  },
  {
    "csatorna": "RTL_HAROM",
    "kezdes": "20260406125000 +0000",
    "vege": "20260406144000 +0000",
    "cim": "Rendőrakadémia 4.: Zseniális amatőrök az utcán"
  },
  {
    "csatorna": "RTL_HAROM",
    "kezdes": "20260406144000 +0000",
    "vege": "20260406163000 +0000",
    "cim": "Rendőrakadémia 5.: Irány Miami Beach"
  },
  {
    "csatorna": "RTL_HAROM",
    "kezdes": "20260406163000 +0000",
    "vege": "20260406182000 +0000",
    "cim": "Rendőrakadémia 6.: Az ostromlott város"
  },
  {
    "csatorna": "RTL_HAROM",
    "kezdes": "20260406182000 +0000",
    "vege": "20260406200000 +0000",
    "cim": "A Rendőrakadémia Moszkvában"
  },
  {
    "csatorna": "RTL_HAROM",
    "kezdes": "20260406200000 +0000",
    "vege": "20260406232000 +0000",
    "cim": "Becstelen brigantyk"
  },
  {
    "csatorna": "RTL_HAROM",
    "kezdes": "20260406232000 +0000",
    "vege": "20260407030000 +0000",
    "cim": "Vadállatok"
  },
  {
    "csatorna": "SUPERTV2",
    "kezdes": "20260406132000 +0000",
    "vege": "20260406151500 +0000",
    "cim": "Míg a jackpot el nem választ"
  },
  {
    "csatorna": "SUPERTV2",
    "kezdes": "20260406151500 +0000",
    "vege": "20260406170000 +0000",
    "cim": "Utazás a rejtélyes szigetre"
  },
  {
    "csatorna": "SUPERTV2",
    "kezdes": "20260406170000 +0000",
    "vege": "20260406180000 +0000",
    "cim": "A mi történetünk"
  },
  {
    "csatorna": "SUPERTV2",
    "kezdes": "20260406180000 +0000",
    "vege": "20260406194500 +0000",
    "cim": "Bérgyilkos Mary"
  },
  {
    "csatorna": "SUPERTV2",
    "kezdes": "20260406194500 +0000",
    "vege": "20260406213000 +0000",
    "cim": "Wasabi - mar, mint a mustár"
  },
  {
    "csatorna": "SUPERTV2",
    "kezdes": "20260406213000 +0000",
    "vege": "20260406231000 +0000",
    "cim": "Jackie, a jó fiú"
  },
  {
    "csatorna": "SUPERTV2",
    "kezdes": "20260406231000 +0000",
    "vege": "20260407000500 +0000",
    "cim": "Magánnyomozók"
  },
  {
    "csatorna": "TV2",
    "kezdes": "20260406125000 +0000",
    "vege": "20260406160000 +0000",
    "cim": "A hobbit: Az öt sereg csatája"
  },
  {
    "csatorna": "TV2",
    "kezdes": "20260406160000 +0000",
    "vege": "20260406164500 +0000",
    "cim": "Tények"
  },
  {
    "csatorna": "TV2",
    "kezdes": "20260406164500 +0000",
    "vege": "20260406180000 +0000",
    "cim": "Tények Plusz"
  },
  {
    "csatorna": "TV2",
    "kezdes": "20260406180000 +0000",
    "vege": "20260406201500 +0000",
    "cim": "Exatlon Hungary"
  },
  {
    "csatorna": "TV2",
    "kezdes": "20260406201500 +0000",
    "vege": "20260406212500 +0000",
    "cim": "A mi történetünk"
  },
  {
    "csatorna": "TV2",
    "kezdes": "20260406212500 +0000",
    "vege": "20260406222000 +0000",
    "cim": "Újratervezés"
  },
  {
    "csatorna": "TV2",
    "kezdes": "20260406222000 +0000",
    "vege": "20260407001000 +0000",
    "cim": "Donor Party"
  },
  {
    "csatorna": "VIASAT3",
    "kezdes": "20260406121000 +0000",
    "vege": "20260406131000 +0000",
    "cim": "Szívek szállodája"
  },
  {
    "csatorna": "VIASAT3",
    "kezdes": "20260406131000 +0000",
    "vege": "20260406141000 +0000",
    "cim": "Szívek szállodája"
  },
  {
    "csatorna": "VIASAT3",
    "kezdes": "20260406141000 +0000",
    "vege": "20260406151000 +0000",
    "cim": "A Grace klinika"
  },
  {
    "csatorna": "VIASAT3",
    "kezdes": "20260406151000 +0000",
    "vege": "20260406160500 +0000",
    "cim": "A Grace klinika"
  },
  {
    "csatorna": "VIASAT3",
    "kezdes": "20260406160500 +0000",
    "vege": "20260406171500 +0000",
    "cim": "A Grace klinika"
  },
  {
    "csatorna": "VIASAT3",
    "kezdes": "20260406171500 +0000",
    "vege": "20260406190000 +0000",
    "cim": "Nagyon vadon"
  },
  {
    "csatorna": "VIASAT3",
    "kezdes": "20260406190000 +0000",
    "vege": "20260406212000 +0000",
    "cim": "Kellékfeleség"
  },
  {
    "csatorna": "VIASAT3",
    "kezdes": "20260406212000 +0000",
    "vege": "20260406233500 +0000",
    "cim": "A szellemlovas"
  },
  {
    "csatorna": "VIASAT3",
    "kezdes": "20260406233500 +0000",
    "vege": "20260407001500 +0000",
    "cim": "A Grace klinika"
  },
  {
    "csatorna": "VIASAT6",
    "kezdes": "20260406124000 +0000",
    "vege": "20260406133500 +0000",
    "cim": "Duma Aktuál"
  },
  {
    "csatorna": "VIASAT6",
    "kezdes": "20260406133500 +0000",
    "vege": "20260406141000 +0000",
    "cim": "A Comedy Central bemutatja"
  },
  {
    "csatorna": "VIASAT6",
    "kezdes": "20260406141000 +0000",
    "vege": "20260406144500 +0000",
    "cim": "A Comedy Central bemutatja"
  },
  {
    "csatorna": "VIASAT6",
    "kezdes": "20260406144500 +0000",
    "vege": "20260406155000 +0000",
    "cim": "Észbontók"
  },
  {
    "csatorna": "VIASAT6",
    "kezdes": "20260406155000 +0000",
    "vege": "20260406165500 +0000",
    "cim": "Észbontók"
  },
  {
    "csatorna": "VIASAT6",
    "kezdes": "20260406165500 +0000",
    "vege": "20260406172500 +0000",
    "cim": "A Comedy Central bemutatja"
  },
  {
    "csatorna": "VIASAT6",
    "kezdes": "20260406172500 +0000",
    "vege": "20260406180000 +0000",
    "cim": "A Comedy Central bemutatja"
  },
  {
    "csatorna": "VIASAT6",
    "kezdes": "20260406180000 +0000",
    "vege": "20260406190000 +0000",
    "cim": "Dumaszínház"
  },
  {
    "csatorna": "VIASAT6",
    "kezdes": "20260406190000 +0000",
    "vege": "20260406200000 +0000",
    "cim": "Duma Aktuál"
  },
  {
    "csatorna": "VIASAT6",
    "kezdes": "20260406200000 +0000",
    "vege": "20260406203500 +0000",
    "cim": "A Comedy Central bemutatja"
  },
  {
    "csatorna": "VIASAT6",
    "kezdes": "20260406203500 +0000",
    "vege": "20260406210500 +0000",
    "cim": "A Comedy Central bemutatja"
  },
  {
    "csatorna": "VIASAT6",
    "kezdes": "20260406210500 +0000",
    "vege": "20260406220000 +0000",
    "cim": "Mogács Dániel: Bolondok Hajója"
  },
  {
    "csatorna": "VIASAT6",
    "kezdes": "20260406220000 +0000",
    "vege": "20260406230000 +0000",
    "cim": "Duma Aktuál"
  },
  {
    "csatorna": "VIASAT6",
    "kezdes": "20260406230000 +0000",
    "vege": "20260407000000 +0000",
    "cim": "Észbontók"
  },
  {
    "csatorna": "VIASAT_FILM",
    "kezdes": "20260406134500 +0000",
    "vege": "20260406164000 +0000",
    "cim": "Erin Brockovich - Zűrös természet"
  },
  {
    "csatorna": "VIASAT_FILM",
    "kezdes": "20260406164000 +0000",
    "vege": "20260406190000 +0000",
    "cim": "Super 8"
  },
  {
    "csatorna": "VIASAT_FILM",
    "kezdes": "20260406190000 +0000",
    "vege": "20260406205500 +0000",
    "cim": "Kipörgetve"
  },
  {
    "csatorna": "VIASAT_FILM",
    "kezdes": "20260406205500 +0000",
    "vege": "20260406225500 +0000",
    "cim": "Úszó erőd"
  },
  {
    "csatorna": "VIASAT_FILM",
    "kezdes": "20260406225500 +0000",
    "vege": "20260407003500 +0000",
    "cim": "Úriember revolverrel"
  }
]